setup.py
pydistributions/Binomialdistribution.py
pydistributions/Gaussiandistribution.py
pydistributions/Generaldistribution.py
pydistributions/__init__.py
pydistributions.egg-info/PKG-INFO
pydistributions.egg-info/SOURCES.txt
pydistributions.egg-info/dependency_links.txt
pydistributions.egg-info/not-zip-safe
pydistributions.egg-info/top_level.txt