Metadata-Version: 1.0
Name: pydistributions
Version: 1.0.0
Summary: Gaussian and Binomial Distributions
Home-page: UNKNOWN
Author: Jay Satija
Author-email: jaysatija712@gmail.com
License: UNKNOWN
Platform: UNKNOWN
